{
  "schema": "fun.lazying.media.catalog.v1",
  "version": 1,
  "site": {
    "name": "Fun Lazying Art",
    "url": "https://fun.lazying.art",
    "protocol": "fun.lazying.media.v1"
  },
  "defaultMedia": "rain-day-bilingual-verse",
  "items": [
    {
      "id": "rain-day-bilingual-verse",
      "kind": "song",
      "title": "Rain Day Trilingual Verse",
      "artist": "Musai SoulX",
      "summary": "A rainy-day vocal demo with three same-timing localized lyric tracks.",
      "manifest": "data/songs/rain-day-bilingual-verse/manifest.json",
      "cover": "assets/covers/rain-day-trilingual-poster-16x9.png",
      "languages": ["zh-Hans", "ja", "en"],
      "tags": ["music", "lyrics", "pinyin", "furigana", "SoulX"]
    }
  ]
}
